{
  "descriptionHash": "223744A768C494F5705EDC83918B16BF1594B792E067D6D37750F64B88B655A385EBDA2D7F2C52BA61A1667C0795BF43F2A28B2DEAC6015F14E1637F322D152E",
  "descriptionLocation": "../../../../tests/8.yaml",
  "lockFileVersion": "1.0.0",
  "kiotaVersion": "1.23.0",
  "clientClassName": "ApiSdk",
  "typeAccessModifier": "Public",
  "clientNamespaceName": "apiSdk",
  "language": "Python",
  "usesBackingStore": false,
  "excludeBackwardCompatible": true,
  "includeAdditionalData": true,
  "disableSSLValidation": false,
  "serializers": [
    "Microsoft.Kiota.Serialization.Json.JsonSerializationWriterFactory",
    "Microsoft.Kiota.Serialization.Text.TextSerializationWriterFactory",
    "Microsoft.Kiota.Serialization.Form.FormSerializationWriterFactory",
    "Microsoft.Kiota.Serialization.Multipart.MultipartSerializationWriterFactory"
  ],
  "deserializers": [
    "Microsoft.Kiota.Serialization.Json.JsonParseNodeFactory",
    "Microsoft.Kiota.Serialization.Text.TextParseNodeFactory",
    "Microsoft.Kiota.Serialization.Form.FormParseNodeFactory"
  ],
  "structuredMimeTypes": [
    "application/json",
    "text/plain;q=0.9",
    "application/x-www-form-urlencoded;q=0.2",
    "multipart/form-data;q=0.1"
  ],
  "includePatterns": [],
  "excludePatterns": [],
  "disabledValidationRules": []
}